carlyleconfig/__init__.py
carlyleconfig/environment.py
carlyleconfig/key.py
carlyleconfig/register.py
carlyleconfig/register.py~
carlyleconfig/utils.py
carlyleconfig/utils.py~
carlyleconfig/plugins/__init__.py
carlyleconfig/plugins/argparse.py
carlyleconfig/plugins/awssecretsmanager.py
carlyleconfig/plugins/awssecretsmanager.py~
carlyleconfig/plugins/base.py
carlyleconfig/plugins/constant.py
carlyleconfig/plugins/default_factory.py
carlyleconfig/plugins/envvar.py
carlyleconfig/plugins/fileparse.py
carlyleconfig/plugins/ssmplugin.py
carlyleconfig-2025.38.1.dist-info/METADATA
carlyleconfig-2025.38.1.dist-info/WHEEL
carlyleconfig-2025.38.1.dist-info/licenses/LICENSE
carlyleconfig-2025.38.1.dist-info/RECORD
